grounded_nlp_toolkit/__init__.py
grounded_nlp_toolkit/nlp_utils.py
grounded_nlp_toolkit-0.0.1.dist-info/WHEEL
grounded_nlp_toolkit-0.0.1.dist-info/METADATA
grounded_nlp_toolkit-0.0.1.dist-info/RECORD
